MANIFEST.in
README.rst
requirements.txt
setup.cfg
setup.py
djmicrosip_orden_trabajo/__init__.py
djmicrosip_orden_trabajo/config.py
djmicrosip_orden_trabajo/forms.py
djmicrosip_orden_trabajo/models.py
djmicrosip_orden_trabajo/storage.py
djmicrosip_orden_trabajo/urls.py
djmicrosip_orden_trabajo/views.py
djmicrosip_orden_trabajo.egg-info/PKG-INFO
djmicrosip_orden_trabajo.egg-info/SOURCES.txt
djmicrosip_orden_trabajo.egg-info/dependency_links.txt
djmicrosip_orden_trabajo.egg-info/requires.txt
djmicrosip_orden_trabajo.egg-info/top_level.txt
djmicrosip_orden_trabajo/__pycache__/__init__.cpython-37.pyc
djmicrosip_orden_trabajo/__pycache__/__init__.cpython-38.pyc
djmicrosip_orden_trabajo/__pycache__/config.cpython-37.pyc
djmicrosip_orden_trabajo/__pycache__/config.cpython-38.pyc
djmicrosip_orden_trabajo/__pycache__/forms.cpython-37.pyc
djmicrosip_orden_trabajo/__pycache__/forms.cpython-38.pyc
djmicrosip_orden_trabajo/__pycache__/models.cpython-37.pyc
djmicrosip_orden_trabajo/__pycache__/models.cpython-38.pyc
djmicrosip_orden_trabajo/__pycache__/storage.cpython-37.pyc
djmicrosip_orden_trabajo/__pycache__/storage.cpython-38.pyc
djmicrosip_orden_trabajo/__pycache__/urls.cpython-37.pyc
djmicrosip_orden_trabajo/__pycache__/urls.cpython-38.pyc
djmicrosip_orden_trabajo/__pycache__/views.cpython-37.pyc
djmicrosip_orden_trabajo/__pycache__/views.cpython-38.pyc
djmicrosip_orden_trabajo/static/djmicrosip_orden_trabajo/css/pedido.css
djmicrosip_orden_trabajo/static/djmicrosip_orden_trabajo/js/firma.js
djmicrosip_orden_trabajo/static/djmicrosip_orden_trabajo/js/index.js
djmicrosip_orden_trabajo/static/djmicrosip_orden_trabajo/js/index2.js
djmicrosip_orden_trabajo/static/djmicrosip_orden_trabajo/js/pedido.js
djmicrosip_orden_trabajo/templates/djmicrosip_orden_trabajo/add_pedido.html
djmicrosip_orden_trabajo/templates/djmicrosip_orden_trabajo/base.html
djmicrosip_orden_trabajo/templates/djmicrosip_orden_trabajo/configuracion.html
djmicrosip_orden_trabajo/templates/djmicrosip_orden_trabajo/firma.html
djmicrosip_orden_trabajo/templates/djmicrosip_orden_trabajo/index.html
djmicrosip_orden_trabajo/templates/djmicrosip_orden_trabajo/lista_pedidos.html
